README.md
setup.cfg
setup.py
Hazem1/Binomialdistribution.py
Hazem1/Gaussiandistribution.py
Hazem1/Generaldistribution.py
Hazem1/__init__.py
Hazem1.egg-info/PKG-INFO
Hazem1.egg-info/SOURCES.txt
Hazem1.egg-info/dependency_links.txt
Hazem1.egg-info/not-zip-safe
Hazem1.egg-info/top_level.txt