Metadata-Version: 1.0
Name: Hazem1
Version: 0.1
Summary: Gaussian distributions and Bionomial 
Home-page: UNKNOWN
Author: Hazem Nuseir
Author-email: hazem.nuseir@gmail.com
License: UNKNOWN
Platform: UNKNOWN
